[
  {"code":"A00","name":"Cólera"},
  {"code":"A02","name":"Otras infecciones por Salmonella"},
  {"code":"A04","name":"Otras infecciones intestinales bacterianas"},
  {"code":"A08","name":"Infecciones intestinales virales"},
  {"code":"A09","name":"Diarrea y gastroenteritis de presunto origen infeccioso"},
  {"code":"A15","name":"Tuberculosis respiratoria, confirmada"},
  {"code":"A41","name":"Otras septicemias"},
  {"code":"A49","name":"Infección bacteriana no especificada"},
  {"code":"A50","name":"Sífilis congénita"},
  {"code":"A53","name":"Sífilis no especificada"},
  {"code":"A54","name":"Infección gonocócica"},
  {"code":"A56","name":"Otras enfermedades de transmisión sexual por clamidias"},
  {"code":"A60","name":"Infección anogenital por virus del herpes simple"},
  {"code":"A63.0","name":"Verrugas anogenitales (venéreas)"},
  {"code":"A71","name":"Tracoma"},
  {"code":"A87","name":"Meningitis viral"},
  {"code":"A90","name":"Fiebre del dengue (dengue clásico)"},
  {"code":"A91","name":"Fiebre del dengue hemorrágico"},
  {"code":"B00","name":"Infecciones herpéticas (herpes simple)"},
  {"code":"B01","name":"Varicela"},
  {"code":"B02","name":"Herpes zoster"},
  {"code":"B05","name":"Sarampión"},
  {"code":"B07","name":"Verrugas víricas"},
  {"code":"B08.4","name":"Estomatitis vesicular enteroviral con exantema"},
  {"code":"B15","name":"Hepatitis aguda tipo A"},
  {"code":"B16","name":"Hepatitis aguda tipo B"},
  {"code":"B17.1","name":"Hepatitis aguda tipo C"},
  {"code":"B18","name":"Hepatitis viral crónica"},
  {"code":"B20","name":"Enfermedad por VIH"},
  {"code":"B26","name":"Parotiditis infecciosa"},
  {"code":"B27","name":"Mononucleosis infecciosa"},
  {"code":"B30","name":"Conjuntivitis viral"},
  {"code":"B34","name":"Infección viral, no especificada"},
  {"code":"B35","name":"Dermatofitosis (tiña)"},
  {"code":"B36","name":"Otras micosis superficiales"},
  {"code":"B37","name":"Candidiasis"},
  {"code":"B37.0","name":"Estomatitis candidiásica"},
  {"code":"B49","name":"Micosis, no especificada"},
  {"code":"B86","name":"Escabiosis"},
  {"code":"B87","name":"Miasis"},
  {"code":"C00","name":"Tumor maligno del labio"},
  {"code":"C02","name":"Tumor maligno de otras partes de la lengua"},
  {"code":"C03","name":"Tumor maligno de la encía"},
  {"code":"C04","name":"Tumor maligno del piso de la boca"},
  {"code":"C06","name":"Tumor maligno de otras partes de la boca"},
  {"code":"C16","name":"Tumor maligno del estómago"},
  {"code":"C18","name":"Tumor maligno del colon"},
  {"code":"C34","name":"Tumor maligno de los bronquios y pulmón"},
  {"code":"C50","name":"Tumor maligno de la mama"},
  {"code":"C53","name":"Tumor maligno del cuello del útero"},
  {"code":"C61","name":"Tumor maligno de la próstata"},
  {"code":"C73","name":"Tumor maligno de la glándula tiroides"},
  {"code":"D17","name":"Tumor lipomatoso benigno"},
  {"code":"D22","name":"Nevos melanocíticos"},
  {"code":"D25","name":"Leiomioma del útero"},
  {"code":"D50","name":"Anemia por deficiencia de hierro"},
  {"code":"D51","name":"Anemia por deficiencia de vitamina B12"},
  {"code":"D52","name":"Anemia por deficiencia de folatos"},
  {"code":"D53","name":"Otras anemias nutricionales"},
  {"code":"D64","name":"Otras anemias"},
  {"code":"E03","name":"Otros hipotiroidismos"},
  {"code":"E04","name":"Otro bocio no tóxico"},
  {"code":"E05","name":"Tirotoxicosis (hipertiroidismo)"},
  {"code":"E07","name":"Otros trastornos de la tiroides"},
  {"code":"E10","name":"Diabetes mellitus insulinodependiente (tipo 1)"},
  {"code":"E11","name":"Diabetes mellitus no insulinodependiente (tipo 2)"},
  {"code":"E11.9","name":"Diabetes mellitus tipo 2, sin mención de complicación"},
  {"code":"E14","name":"Diabetes mellitus, no especificada"},
  {"code":"E16","name":"Otros trastornos de la secreción interna del páncreas"},
  {"code":"E27","name":"Otros trastornos de la glándula suprarrenal"},
  {"code":"E28","name":"Disfunción ovárica"},
  {"code":"E34","name":"Otros trastornos endocrinos"},
  {"code":"E40","name":"Kwashiorkor"},
  {"code":"E44","name":"Desnutrición proteicocalórica de grado moderado y leve"},
  {"code":"E55","name":"Deficiencia de vitamina D"},
  {"code":"E56","name":"Otras deficiencias vitamínicas"},
  {"code":"E61","name":"Deficiencia de otros elementos nutricionales"},
  {"code":"E66","name":"Obesidad"},
  {"code":"E66.0","name":"Obesidad debida a exceso de calorías"},
  {"code":"E66.9","name":"Obesidad, no especificada"},
  {"code":"E73","name":"Intolerancia a la lactosa"},
  {"code":"E78","name":"Trastornos del metabolismo de las lipoproteínas (dislipidemia)"},
  {"code":"E78.0","name":"Hipercolesterolemia pura"},
  {"code":"E78.5","name":"Hiperlipidemia mixta"},
  {"code":"E79","name":"Trastornos del metabolismo de las purinas y pirimidinas"},
  {"code":"E83","name":"Trastornos del metabolismo de los minerales"},
  {"code":"E86","name":"Depleción del volumen (deshidratación)"},
  {"code":"E87","name":"Otros trastornos de los líquidos, electrólitos y equilibrio ácido-básico"},
  {"code":"F10","name":"Trastornos mentales por consumo de alcohol"},
  {"code":"F17","name":"Trastornos mentales por consumo de tabaco"},
  {"code":"F19","name":"Trastornos mentales por consumo de múltiples drogas"},
  {"code":"F20","name":"Esquizofrenia"},
  {"code":"F31","name":"Trastorno afectivo bipolar"},
  {"code":"F32","name":"Episodio depresivo"},
  {"code":"F32.9","name":"Episodio depresivo, no especificado"},
  {"code":"F33","name":"Trastorno depresivo recurrente"},
  {"code":"F40","name":"Trastornos fóbicos de ansiedad"},
  {"code":"F41","name":"Otros trastornos de ansiedad"},
  {"code":"F41.0","name":"Trastorno de pánico"},
  {"code":"F41.1","name":"Trastorno de ansiedad generalizada"},
  {"code":"F43","name":"Reacciones a estrés grave y trastornos de adaptación"},
  {"code":"F45","name":"Trastornos somatomorfos"},
  {"code":"F50","name":"Trastornos de la conducta alimentaria"},
  {"code":"F51","name":"Trastornos no orgánicos del sueño"},
  {"code":"F60","name":"Trastornos específicos de la personalidad"},
  {"code":"F70","name":"Retraso mental leve"},
  {"code":"F84","name":"Trastornos generalizados del desarrollo (TEA)"},
  {"code":"F90","name":"Trastornos hipercinéticos (TDAH)"},
  {"code":"G40","name":"Epilepsia"},
  {"code":"G43","name":"Migraña"},
  {"code":"G43.9","name":"Migraña no especificada"},
  {"code":"G44","name":"Otros síndromes de cefalea"},
  {"code":"G44.2","name":"Cefalea debida a tensión"},
  {"code":"G45","name":"Ataques de isquemia cerebral transitoria"},
  {"code":"G47","name":"Trastornos del sueño"},
  {"code":"G50","name":"Trastornos del nervio trigémino"},
  {"code":"G51","name":"Trastornos del nervio facial"},
  {"code":"G54","name":"Trastornos de las raíces y plexos nerviosos"},
  {"code":"G56","name":"Mononeuropatías del miembro superior"},
  {"code":"G56.0","name":"Síndrome del túnel carpiano"},
  {"code":"G62","name":"Otras polineuropatías"},
  {"code":"G81","name":"Hemiplejía"},
  {"code":"G93","name":"Otros trastornos del encéfalo"},
  {"code":"H10","name":"Conjuntivitis"},
  {"code":"H11","name":"Otros trastornos de la conjuntiva"},
  {"code":"H16","name":"Queratitis"},
  {"code":"H25","name":"Catarata senil"},
  {"code":"H26","name":"Otras cataratas"},
  {"code":"H40","name":"Glaucoma"},
  {"code":"H52","name":"Trastornos de la acomodación y refracción"},
  {"code":"H52.0","name":"Hipermetropía"},
  {"code":"H52.1","name":"Miopía"},
  {"code":"H52.2","name":"Astigmatismo"},
  {"code":"H52.4","name":"Presbicia"},
  {"code":"H53","name":"Alteraciones visuales"},
  {"code":"H60","name":"Otitis externa"},
  {"code":"H65","name":"Otitis media no supurativa"},
  {"code":"H66","name":"Otitis media supurativa y la no especificada"},
  {"code":"H66.9","name":"Otitis media, no especificada"},
  {"code":"H70","name":"Mastoiditis y enfermedades relacionadas"},
  {"code":"H81","name":"Trastornos de la función vestibular (vértigo)"},
  {"code":"H90","name":"Hipoacusia conductiva y neurosensorial"},
  {"code":"H93","name":"Otros trastornos del oído (tinnitus)"},
  {"code":"I10","name":"Hipertensión esencial (primaria)"},
  {"code":"I11","name":"Enfermedad cardíaca hipertensiva"},
  {"code":"I12","name":"Enfermedad renal hipertensiva"},
  {"code":"I20","name":"Angina de pecho"},
  {"code":"I21","name":"Infarto agudo del miocardio"},
  {"code":"I25","name":"Enfermedad isquémica crónica del corazón"},
  {"code":"I48","name":"Fibrilación y aleteo auricular"},
  {"code":"I50","name":"Insuficiencia cardíaca"},
  {"code":"I63","name":"Infarto cerebral"},
  {"code":"I64","name":"Accidente vascular encefálico (ACV)"},
  {"code":"I65","name":"Oclusión y estenosis de arterias precerebrales"},
  {"code":"I70","name":"Aterosclerosis"},
  {"code":"I80","name":"Flebitis y tromboflebitis"},
  {"code":"I83","name":"Várices de los miembros inferiores"},
  {"code":"I84","name":"Hemorroides"},
  {"code":"I86.1","name":"Várices escrotales"},
  {"code":"I87","name":"Otros trastornos de las venas"},
  {"code":"I95","name":"Hipotensión"},
  {"code":"J00","name":"Rinofaringitis aguda (resfriado común)"},
  {"code":"J01","name":"Sinusitis aguda"},
  {"code":"J02","name":"Faringitis aguda"},
  {"code":"J02.9","name":"Faringitis aguda, no especificada"},
  {"code":"J03","name":"Amigdalitis aguda"},
  {"code":"J03.9","name":"Amigdalitis aguda, no especificada"},
  {"code":"J04","name":"Laringitis y traqueítis agudas"},
  {"code":"J05","name":"Laringitis obstructiva aguda (crup)"},
  {"code":"J06","name":"Infecciones agudas de las vías respiratorias superiores"},
  {"code":"J11","name":"Influenza debida a virus no identificado"},
  {"code":"J12","name":"Neumonía viral"},
  {"code":"J13","name":"Neumonía por Streptococcus pneumoniae"},
  {"code":"J15","name":"Neumonía bacteriana"},
  {"code":"J18","name":"Neumonía, organismo no especificado"},
  {"code":"J20","name":"Bronquitis aguda"},
  {"code":"J21","name":"Bronquiolitis aguda"},
  {"code":"J30","name":"Rinitis alérgica"},
  {"code":"J32","name":"Sinusitis crónica"},
  {"code":"J35","name":"Enfermedades crónicas de las amígdalas y adenoides"},
  {"code":"J42","name":"Bronquitis crónica no especificada"},
  {"code":"J44","name":"Enfermedad pulmonar obstructiva crónica (EPOC)"},
  {"code":"J45","name":"Asma"},
  {"code":"J45.9","name":"Asma, no especificada"},
  {"code":"J46","name":"Estado asmático"},
  {"code":"K00","name":"Trastornos del desarrollo y de la erupción de los dientes"},
  {"code":"K00.0","name":"Anodoncia"},
  {"code":"K00.2","name":"Anomalías del tamaño y de la forma del diente"},
  {"code":"K00.6","name":"Trastornos de la erupción dental"},
  {"code":"K01","name":"Dientes incluidos e impactados"},
  {"code":"K02","name":"Caries dental"},
  {"code":"K02.1","name":"Caries de la dentina"},
  {"code":"K02.2","name":"Caries del cemento"},
  {"code":"K02.3","name":"Caries dental detenida"},
  {"code":"K02.5","name":"Caries con exposición de la pulpa"},
  {"code":"K02.9","name":"Caries dental, no especificada"},
  {"code":"K03","name":"Otras enfermedades de los tejidos duros de los dientes"},
  {"code":"K03.0","name":"Atrición excesiva de los dientes"},
  {"code":"K03.2","name":"Erosión de los dientes"},
  {"code":"K03.6","name":"Depósitos (acreciones) en los dientes (cálculo dental, sarro)"},
  {"code":"K03.8","name":"Otras enfermedades especificadas de los tejidos duros (hipersensibilidad dentinaria)"},
  {"code":"K04","name":"Enfermedades de la pulpa y de los tejidos periapicales"},
  {"code":"K04.0","name":"Pulpitis"},
  {"code":"K04.1","name":"Necrosis de la pulpa"},
  {"code":"K04.4","name":"Periodontitis apical aguda"},
  {"code":"K04.5","name":"Periodontitis apical crónica"},
  {"code":"K04.6","name":"Absceso periapical con fístula"},
  {"code":"K04.7","name":"Absceso periapical sin fístula"},
  {"code":"K05","name":"Gingivitis y enfermedades periodontales"},
  {"code":"K05.0","name":"Gingivitis aguda"},
  {"code":"K05.1","name":"Gingivitis crónica"},
  {"code":"K05.2","name":"Periodontitis aguda"},
  {"code":"K05.3","name":"Periodontitis crónica"},
  {"code":"K05.4","name":"Periodontosis"},
  {"code":"K05.5","name":"Otras enfermedades periodontales"},
  {"code":"K05.6","name":"Enfermedad del periodonto, no especificada"},
  {"code":"K06","name":"Otros trastornos de la encía y de la zona edéntula"},
  {"code":"K06.0","name":"Retracción gingival"},
  {"code":"K06.1","name":"Hiperplasia gingival"},
  {"code":"K07","name":"Anomalías dentofaciales (incluso la maloclusión)"},
  {"code":"K07.3","name":"Anomalías de la posición del diente (apiñamiento)"},
  {"code":"K07.4","name":"Maloclusión no especificada"},
  {"code":"K07.6","name":"Trastornos de la articulación temporomandibular (ATM)"},
  {"code":"K08","name":"Otros trastornos de los dientes y de sus estructuras de sostén"},
  {"code":"K08.1","name":"Pérdida de dientes debida a accidente, extracción o enfermedad periodontal local"},
  {"code":"K08.3","name":"Raíz dental retenida"},
  {"code":"K09","name":"Quistes de la región bucal, no clasificados en otra parte"},
  {"code":"K10","name":"Otras enfermedades de los maxilares"},
  {"code":"K11","name":"Enfermedades de las glándulas salivales"},
  {"code":"K11.2","name":"Sialoadenitis"},
  {"code":"K11.5","name":"Sialolitiasis"},
  {"code":"K12","name":"Estomatitis y lesiones afines"},
  {"code":"K12.0","name":"Estomatitis aftosa recurrente"},
  {"code":"K12.1","name":"Otras formas de estomatitis"},
  {"code":"K13","name":"Otras enfermedades del labio y de la mucosa bucal"},
  {"code":"K13.0","name":"Enfermedades de los labios (queilitis)"},
  {"code":"K14","name":"Enfermedades de la lengua"},
  {"code":"K14.0","name":"Glositis"},
  {"code":"K20","name":"Esofagitis"},
  {"code":"K21","name":"Enfermedad del reflujo gastroesofágico (ERGE)"},
  {"code":"K25","name":"Úlcera gástrica"},
  {"code":"K26","name":"Úlcera duodenal"},
  {"code":"K29","name":"Gastritis y duodenitis"},
  {"code":"K29.7","name":"Gastritis, no especificada"},
  {"code":"K30","name":"Dispepsia"},
  {"code":"K35","name":"Apendicitis aguda"},
  {"code":"K40","name":"Hernia inguinal"},
  {"code":"K42","name":"Hernia umbilical"},
  {"code":"K43","name":"Hernia ventral"},
  {"code":"K52","name":"Otras gastroenteritis y colitis no infecciosas"},
  {"code":"K58","name":"Síndrome del colon irritable"},
  {"code":"K59","name":"Otros trastornos funcionales del intestino"},
  {"code":"K59.0","name":"Constipación"},
  {"code":"K60","name":"Fisura y fístula de las regiones anal y rectal"},
  {"code":"K70","name":"Enfermedad alcohólica del hígado"},
  {"code":"K80","name":"Colelitiasis"},
  {"code":"K81","name":"Colecistitis"},
  {"code":"K85","name":"Pancreatitis aguda"},
  {"code":"K92","name":"Otras enfermedades del sistema digestivo"},
  {"code":"L01","name":"Impétigo"},
  {"code":"L02","name":"Absceso cutáneo, furúnculo y carbunco"},
  {"code":"L03","name":"Celulitis"},
  {"code":"L20","name":"Dermatitis atópica"},
  {"code":"L21","name":"Dermatitis seborreica"},
  {"code":"L23","name":"Dermatitis alérgica de contacto"},
  {"code":"L25","name":"Dermatitis de contacto, no especificada"},
  {"code":"L29","name":"Prurito"},
  {"code":"L30","name":"Otras dermatitis"},
  {"code":"L40","name":"Psoriasis"},
  {"code":"L50","name":"Urticaria"},
  {"code":"L70","name":"Acné"},
  {"code":"L70.0","name":"Acné vulgar"},
  {"code":"L71","name":"Rosácea"},
  {"code":"L81","name":"Otros trastornos de la pigmentación"},
  {"code":"L82","name":"Queratosis seborreica"},
  {"code":"L90","name":"Trastornos atróficos de la piel"},
  {"code":"L91","name":"Trastornos hipertróficos de la piel"},
  {"code":"M05","name":"Artritis reumatoide seropositiva"},
  {"code":"M10","name":"Gota"},
  {"code":"M15","name":"Poliartrosis"},
  {"code":"M17","name":"Gonartrosis (artrosis de rodilla)"},
  {"code":"M19","name":"Otras artrosis"},
  {"code":"M25","name":"Otros trastornos articulares no clasificados"},
  {"code":"M40","name":"Cifosis y lordosis"},
  {"code":"M41","name":"Escoliosis"},
  {"code":"M42","name":"Osteocondrosis de la columna vertebral"},
  {"code":"M47","name":"Espondilosis"},
  {"code":"M48","name":"Otras espondilopatías"},
  {"code":"M50","name":"Trastornos de los discos cervicales"},
  {"code":"M51","name":"Otros trastornos de los discos intervertebrales"},
  {"code":"M54","name":"Dorsalgia"},
  {"code":"M54.2","name":"Cervicalgia"},
  {"code":"M54.5","name":"Lumbago no especificado"},
  {"code":"M54.6","name":"Dolor en la región torácica de la columna"},
  {"code":"M62","name":"Otros trastornos de los músculos"},
  {"code":"M65","name":"Sinovitis y tenosinovitis"},
  {"code":"M75","name":"Lesiones del hombro"},
  {"code":"M77","name":"Otras entesopatías (epicondilitis)"},
  {"code":"M79","name":"Otros trastornos de los tejidos blandos"},
  {"code":"M79.6","name":"Dolor en miembro"},
  {"code":"M81","name":"Osteoporosis sin fractura patológica"},
  {"code":"N10","name":"Nefritis tubulointersticial aguda"},
  {"code":"N17","name":"Insuficiencia renal aguda"},
  {"code":"N18","name":"Insuficiencia renal crónica"},
  {"code":"N20","name":"Cálculo del riñón y del uréter"},
  {"code":"N30","name":"Cistitis"},
  {"code":"N39","name":"Otros trastornos del sistema urinario"},
  {"code":"N39.0","name":"Infección de vías urinarias, sitio no especificado"},
  {"code":"N40","name":"Hiperplasia de la próstata"},
  {"code":"N41","name":"Enfermedades inflamatorias de la próstata"},
  {"code":"N45","name":"Orquitis y epididimitis"},
  {"code":"N60","name":"Displasia mamaria benigna"},
  {"code":"N70","name":"Salpingitis y ooforitis"},
  {"code":"N72","name":"Enfermedad inflamatoria del cuello uterino"},
  {"code":"N73","name":"Otras enfermedades pélvicas inflamatorias femeninas"},
  {"code":"N76","name":"Otras afecciones inflamatorias de la vagina y de la vulva"},
  {"code":"N80","name":"Endometriosis"},
  {"code":"N84","name":"Pólipo del tracto genital femenino"},
  {"code":"N91","name":"Menstruación ausente, escasa o rara"},
  {"code":"N92","name":"Menstruación excesiva, frecuente e irregular"},
  {"code":"N93","name":"Otras hemorragias uterinas o vaginales anormales"},
  {"code":"N94","name":"Dolor y otras afecciones relacionadas con la menstruación"},
  {"code":"N95","name":"Trastornos menopáusicos y otros perimenopáusicos"},
  {"code":"N97","name":"Infertilidad femenina"},
  {"code":"O09","name":"Duración del embarazo"},
  {"code":"O14","name":"Hipertensión gestacional con proteinuria"},
  {"code":"O20","name":"Hemorragia precoz del embarazo"},
  {"code":"O21","name":"Vómitos excesivos en el embarazo"},
  {"code":"O24","name":"Diabetes mellitus en el embarazo"},
  {"code":"O80","name":"Parto único espontáneo"},
  {"code":"P59","name":"Ictericia neonatal por otras causas"},
  {"code":"Q35","name":"Fisura del paladar (paladar hendido)"},
  {"code":"Q36","name":"Labio leporino"},
  {"code":"Q37","name":"Fisura del paladar con labio leporino"},
  {"code":"R05","name":"Tos"},
  {"code":"R06","name":"Anormalidades de la respiración"},
  {"code":"R07","name":"Dolor de garganta y de tórax"},
  {"code":"R10","name":"Dolor abdominal y pélvico"},
  {"code":"R10.4","name":"Otros dolores abdominales y los no especificados"},
  {"code":"R11","name":"Náusea y vómito"},
  {"code":"R14","name":"Flatulencia y afecciones afines"},
  {"code":"R19","name":"Otros síntomas y signos que involucran el sistema digestivo"},
  {"code":"R21","name":"Salpullido y otras erupciones cutáneas no especificadas"},
  {"code":"R30","name":"Dolor asociado a la micción"},
  {"code":"R31","name":"Hematuria, no especificada"},
  {"code":"R33","name":"Retención de orina"},
  {"code":"R42","name":"Mareo y desvanecimiento"},
  {"code":"R50","name":"Fiebre de origen desconocido"},
  {"code":"R51","name":"Cefalea"},
  {"code":"R52","name":"Dolor, no clasificado en otra parte"},
  {"code":"R53","name":"Malestar y fatiga"},
  {"code":"R55","name":"Síncope y colapso"},
  {"code":"R60","name":"Edema, no clasificado en otra parte"},
  {"code":"R63","name":"Síntomas y signos relativos a la ingestión de alimentos y líquidos"},
  {"code":"R69","name":"Causas de morbilidad desconocidas y no especificadas"},
  {"code":"S00","name":"Traumatismo superficial de la cabeza"},
  {"code":"S01","name":"Herida de la cabeza"},
  {"code":"S02","name":"Fractura de huesos del cráneo y de la cara"},
  {"code":"S03","name":"Luxación, esguince y desgarro de articulaciones y ligamentos de la cabeza"},
  {"code":"S03.0","name":"Luxación del maxilar inferior (ATM)"},
  {"code":"S06","name":"Traumatismo intracraneal"},
  {"code":"S09.1","name":"Avulsión del diente"},
  {"code":"S10","name":"Traumatismo superficial del cuello"},
  {"code":"S20","name":"Traumatismo superficial del tórax"},
  {"code":"S40","name":"Traumatismo superficial del hombro y del brazo"},
  {"code":"S43","name":"Luxación, esguince y desgarro de articulaciones y ligamentos de cintura escapular"},
  {"code":"S52","name":"Fractura del antebrazo"},
  {"code":"S60","name":"Traumatismo superficial de la muñeca y de la mano"},
  {"code":"S63","name":"Luxación, esguince y desgarro de articulaciones y ligamentos a nivel de la muñeca"},
  {"code":"S72","name":"Fractura del fémur"},
  {"code":"S82","name":"Fractura de la pierna, inclusive del tobillo"},
  {"code":"S83","name":"Luxación, esguince y desgarro de articulaciones y ligamentos de la rodilla"},
  {"code":"S90","name":"Traumatismo superficial del tobillo y del pie"},
  {"code":"T14","name":"Traumatismo de región no especificada del cuerpo"},
  {"code":"T78","name":"Efectos adversos no clasificados en otra parte"},
  {"code":"T78.2","name":"Choque anafiláctico, no especificado"},
  {"code":"T78.4","name":"Alergia, no especificada"},
  {"code":"T88","name":"Otras complicaciones de la atención médica"},
  {"code":"Z00","name":"Examen general e investigación de personas sin quejas o sin diagnóstico"},
  {"code":"Z01","name":"Otros exámenes especiales e investigaciones de personas sin quejas o sin diagnóstico"},
  {"code":"Z01.2","name":"Examen odontológico"},
  {"code":"Z02","name":"Examen y consulta con propósito administrativo"},
  {"code":"Z23","name":"Necesidad de inmunización"},
  {"code":"Z30","name":"Atención para la anticoncepción"},
  {"code":"Z33","name":"Estado de embarazo, incidental"},
  {"code":"Z34","name":"Supervisión de embarazo normal"},
  {"code":"Z39","name":"Examen y atención del posparto"},
  {"code":"Z51","name":"Otra atención médica especificada"},
  {"code":"Z71","name":"Personas en contacto con los servicios de salud por otras consultas y consejo médico"},
  {"code":"Z72","name":"Problemas relacionados con el estilo de vida"},
  {"code":"Z76","name":"Personas que reciben atención médica por otras circunstancias"}
]
